MANIFEST.in
README.markdown
setup.py
smpp/__init__.py
smpp.pdu.egg-info/PKG-INFO
smpp.pdu.egg-info/SOURCES.txt
smpp.pdu.egg-info/dependency_links.txt
smpp.pdu.egg-info/not-zip-safe
smpp.pdu.egg-info/requires.txt
smpp.pdu.egg-info/top_level.txt
smpp/pdu/__init__.py
smpp/pdu/constants.py
smpp/pdu/encoding.py
smpp/pdu/error.py
smpp/pdu/gsm_constants.py
smpp/pdu/gsm_encoding.py
smpp/pdu/gsm_types.py
smpp/pdu/namedtuple.py
smpp/pdu/operations.py
smpp/pdu/pdu_encoding.py
smpp/pdu/pdu_types.py
smpp/pdu/sm_encoding.py
smpp/pdu/smpp_time.py
smpp/pdu/tests/__init__.py
smpp/pdu/tests/gsm_encoding_test.py
smpp/pdu/tests/pdu_encoding_test.py
smpp/pdu/tests/pdu_types_test.py
smpp/pdu/tests/sm_encoding_test.py
smpp/pdu/tests/smpp_time_test.py