Metadata-Version: 1.0
Name: smpp.pdu
Version: 0.3
Summary: Library for parsing Protocol Data Units (PDUs) in SMPP protocol
Home-page: https://github.com/mozes/smpp.pdu
Author: Roger Hoover
Author-email: roger.hoover@gmail.com
License: Apache License 2.0
Keywords: smpp pdu
Platform: UNKNOWN
Classifier: Development Status :: 5 - Production/Stable
Classifier: Topic :: System :: Networking
Classifier: Operating System :: OS Independent
Classifier: License :: OSI Approved :: Apache Software License
Classifier: Intended Audience :: Developers
Classifier: Programming Language :: Python
Classifier: Topic :: Software Development :: Libraries :: Python Modules
